convnet/__init__.py
convnet/data.py
convnet/io.py
convnet/jax_backend.py
convnet/layers.py
convnet/losses.py
convnet/model.py
convnet/numba_ops.py
convnet/optim.py
convnet/utils.py
convnet-2.2.0.dist-info/licenses/LICENSE.md
convnet-2.2.0.dist-info/METADATA
convnet-2.2.0.dist-info/WHEEL
convnet-2.2.0.dist-info/top_level.txt
convnet-2.2.0.dist-info/RECORD
