Metadata-Version: 2.4
Name: convnet
Version: 2.2.0
Summary: A high-performance CNN framework: Numba for CPU, JAX for GPU/TPU
Home-page: https://github.com/codinggamer-dev/ConvNet-NumPy
Author: codinggamer-dev
Author-email: ege.tba1940@gmail.com
Project-URL: Bug Reports, https://github.com/codinggamer-dev/ConvNet-NumPy/issues
Project-URL: Source, https://github.com/codinggamer-dev/ConvNet-NumPy
Keywords: deep-learning neural-network cnn convolutional jax gpu education scratch python
Classifier: Development Status :: 4 - Beta
Classifier: Intended Audience :: Education
Classifier: Intended Audience :: Science/Research
Classifier: License :: OSI Approved :: MIT License
Classifier: Programming Language :: Python :: 3
Classifier: Programming Language :: Python :: 3.8
Classifier: Programming Language :: Python :: 3.9
Classifier: Programming Language :: Python :: 3.10
Classifier: Programming Language :: Python :: 3.11
Classifier: Programming Language :: Python :: 3.12
Classifier: Topic :: Scientific/Engineering :: Artificial Intelligence
Classifier: Topic :: Education
Requires-Python: >=3.8
License-File: LICENSE.md
Requires-Dist: numpy>=1.20.0
Requires-Dist: numba>=0.56.0
Requires-Dist: tqdm>=4.60.0
Requires-Dist: h5py>=3.0.0
Provides-Extra: jax
Requires-Dist: jax>=0.4.0; extra == "jax"
Requires-Dist: jaxlib>=0.4.0; extra == "jax"
Provides-Extra: gpu
Requires-Dist: jax[cuda12]; extra == "gpu"
Provides-Extra: tpu
Requires-Dist: jax[tpu]; extra == "tpu"
Provides-Extra: dev
Requires-Dist: pytest>=6.0.0; extra == "dev"
Requires-Dist: black>=21.0.0; extra == "dev"
Requires-Dist: flake8>=3.8.0; extra == "dev"
Dynamic: author
Dynamic: author-email
Dynamic: classifier
Dynamic: description
Dynamic: description-content-type
Dynamic: home-page
Dynamic: keywords
Dynamic: license-file
Dynamic: project-url
Dynamic: provides-extra
Dynamic: requires-dist
Dynamic: requires-python
Dynamic: summary
